Metadata-Version: 2.4
Name: gptsh-cli
Version: 0.8.2
License-Expression: Apache-2.0
Requires-Python: >=3.10
License-File: LICENSE
Requires-Dist: click
Requires-Dist: httpx
Requires-Dist: litellm
Requires-Dist: mcp>=1.15.0
Requires-Dist: prompt_toolkit>=3.0.0
Requires-Dist: python-dotenv
Requires-Dist: pyyaml
Requires-Dist: rich
Requires-Dist: pasteboard>=0.3.3; sys_platform == "darwin"
Provides-Extra: dev
Requires-Dist: pytest; extra == "dev"
Requires-Dist: pytest-asyncio; extra == "dev"
Requires-Dist: ruff; extra == "dev"
Dynamic: license-file
